{
  "os":  "macOS-14.4-arm64-arm-64bit-Mach-O",
  "python":  "CPython 3.13.5",
  "startedAt":  "2025-07-27T22:44:37.581316Z",
  "program":  "/Users/minjunes/vcc/train_mini_diffusion.py",
  "codePath":  "train_mini_diffusion.py",
  "codePathLocal":  "train_mini_diffusion.py",
  "git":  {
    "remote":  "https://github.com/pythonlearner1025/vcc.git",
    "commit":  "88359c9d9fe15ce15fdad188cfdcf643bfd70ba1"
  },
  "email":  "mjsong2021@gmail.com",
  "root":  "/Users/minjunes/vcc",
  "host":  "Minjunes-MacBook-Pro-3.local",
  "executable":  "/Users/minjunes/vcc/env/bin/python3",
  "writerId":  "0bomoic0g8vn20cq6zww1pjjbdb97826"
}